aprsd_wxnow_plugin/__init__.py
aprsd_wxnow_plugin/aprsd_wxnow_plugin.py
aprsd_wxnow_plugin/conf/__init__.py
aprsd_wxnow_plugin/conf/main.py
aprsd_wxnow_plugin/conf/opts.py
aprsd_wxnow_plugin-0.2.0.dist-info/LICENSE
aprsd_wxnow_plugin-0.2.0.dist-info/METADATA
aprsd_wxnow_plugin-0.2.0.dist-info/WHEEL
aprsd_wxnow_plugin-0.2.0.dist-info/entry_points.txt
aprsd_wxnow_plugin-0.2.0.dist-info/pbr.json
aprsd_wxnow_plugin-0.2.0.dist-info/top_level.txt
aprsd_wxnow_plugin-0.2.0.dist-info/RECORD
